escprint/__init__.py
escprint/esc.py
escprint-1.0.4.dist-info/LICENSE.txt
escprint-1.0.4.dist-info/METADATA
escprint-1.0.4.dist-info/WHEEL
escprint-1.0.4.dist-info/top_level.txt
escprint-1.0.4.dist-info/RECORD
