Metadata-Version: 2.1
Name: escprint
Version: 1.0.4
Summary: Library for formatting and styling terminal outputs via ANSI escape sequences.
Home-page: https://github.com/michaelmunson/escprint
Author: Michael Munson
Author-email: michael.s.munson@outlook.com
Project-URL: Bug Tracker, https://github.com/michaelmunson/escprint/issues
Project-URL: repository, https://github.com/michaelmunson/escprint
Classifier: Programming Language :: Python :: 3
Classifier: License :: OSI Approved :: MIT License
Classifier: Operating System :: OS Independent
Requires-Python: >=3.6
License-File: LICENSE.txt
